zylo_docs/__init__.py
zylo_docs/data/all_schemas.json
zylo_docs/integration.py
zylo_docs/middlewares/exception_handler.py
zylo_docs/routers/front_route.py
zylo_docs/routers/proxy_route.py
zylo_docs/schemas/response.py
zylo_docs/schemas/schema_data.py
zylo_docs/services/user_server_service.py
zylo_docs/static/assets/index-CtNYeh24.js
zylo_docs/static/assets/index-Cv8cYcgs.css
zylo_docs/static/index.html
zylo_docs_test-0.1.10.dist-info/METADATA
zylo_docs_test-0.1.10.dist-info/WHEEL
zylo_docs_test-0.1.10.dist-info/entry_points.txt
zylo_docs_test-0.1.10.dist-info/RECORD
