Metadata-Version: 2.3
Name: zylo-docs-test
Version: 0.1.10
Summary: 
Author: lee gyu yeol-mac
Author-email: i1004gy@gmail.com
Requires-Python: >=3.10
Classifier: Programming Language :: Python :: 3
Classifier: Programming Language :: Python :: 3.10
Classifier: Programming Language :: Python :: 3.11
Classifier: Programming Language :: Python :: 3.12
Classifier: Programming Language :: Python :: 3.13
Requires-Dist: click (>=8.1.3,<9.0.0)
Requires-Dist: fastapi (>=0.115.10,<0.116.0)
Requires-Dist: httpx (>=0.27.1,<0.29.0)
Requires-Dist: uvicorn[standard] (>=0.34.0,<0.36.0)
